CHANGELOG.md
LICENSE
MANIFEST.in
README.md
setup.cfg
setup.py
pip_services_logging/__init__.py
pip_services_logging.egg-info/PKG-INFO
pip_services_logging.egg-info/SOURCES.txt
pip_services_logging.egg-info/dependency_links.txt
pip_services_logging.egg-info/requires.txt
pip_services_logging.egg-info/top_level.txt
pip_services_logging.egg-info/zip-safe
pip_services_logging/build/LoggingFactory.py
pip_services_logging/build/__init__.py
pip_services_logging/container/LoggingProcess.py
pip_services_logging/container/__init__.py
pip_services_logging/data/__init__.py
pip_services_logging/data/version1/LogMessageV1.py
pip_services_logging/data/version1/__init__.py
pip_services_logging/logic/ILoggingBusinessLogic.py
pip_services_logging/logic/LoggingCommandSet.py
pip_services_logging/logic/LoggingController.py
pip_services_logging/logic/__init__.py
pip_services_logging/persistence/ILoggingPersistence.py
pip_services_logging/persistence/LoggingMemoryPersistence.py
pip_services_logging/persistence/__init__.py
pip_services_logging/services/__init__.py
pip_services_logging/services/version1/LoggingHttpServiceV1.py
pip_services_logging/services/version1/__init__.py